mdvcontainment/__init__.py
mdvcontainment/_version.py
mdvcontainment/atoms_voxels_mapping.cpython-314-darwin.so
mdvcontainment/composition_logic.py
mdvcontainment/find_bridges.cpython-314-darwin.so
mdvcontainment/find_label_contacts.cpython-314-darwin.so
mdvcontainment/gen_data_helper.py
mdvcontainment/graph_logic.py
mdvcontainment/label_logic.py
mdvcontainment/mda_containment.py
mdvcontainment/rank_logic.py
mdvcontainment/voxel_containment.py
mdvcontainment/voxel_logic.py
mdvcontainment/wrappers.py
mdvcontainment-2.0.0.post1.dist-info/licenses/LICENSE
mdvcontainment-2.0.0.post1.dist-info/METADATA
mdvcontainment-2.0.0.post1.dist-info/WHEEL
mdvcontainment-2.0.0.post1.dist-info/top_level.txt
mdvcontainment-2.0.0.post1.dist-info/RECORD
