Metadata-Version: 2.4
Name: mdvcontainment
Version: 2.0.0.post1
Summary: Containment analysis for (periodic) point clouds.
Home-page: https://github.com/BartBruininks/mdvcontainment
Author: BMH Bruininks
Requires-Python: >=3.12
License-File: LICENSE
Requires-Dist: numpy>=2.2
Requires-Dist: networkx>=3.4
Requires-Dist: scipy>=1.15
Requires-Dist: MDAnalysis>=2.8
Requires-Dist: matplotlib>=3.10
Dynamic: author
Dynamic: description
Dynamic: description-content-type
Dynamic: home-page
Dynamic: license-file
Dynamic: requires-dist
Dynamic: requires-python
Dynamic: summary
